ttps/__init__.py
ttps/__main__.py
ttps-0.0.0.dist-info/METADATA
ttps-0.0.0.dist-info/WHEEL
ttps-0.0.0.dist-info/entry_points.txt
ttps-0.0.0.dist-info/top_level.txt
ttps-0.0.0.dist-info/RECORD
